{
  "stats": {
    "suites": 1,
    "tests": 5,
    "passes": 5,
    "pending": 0,
    "failures": 0,
    "testsRegistered": 5,
    "passPercent": 100,
    "pendingPercent": 0,
    "other": 0,
    "hasOther": false,
    "skipped": 0,
    "hasSkipped": false,
    "start": "2024-07-30T15:23:09.381Z",
    "end": "2024-07-30T15:23:12.385Z",
    "duration": 3004
  },
  "results": [
    {
      "uuid": "57e60a9f-c164-42b5-b8dd-3e424888c9cf",
      "title": "",
      "fullFile": "cypress\\e2e\\home.cy.ts",
      "file": "cypress\\e2e\\home.cy.ts",
      "beforeHooks": [],
      "afterHooks": [],
      "tests": [],
      "suites": [
        {
          "uuid": "14620931-4fb3-4436-825d-6c1e4b9474af",
          "title": "Ponyracer",
          "fullFile": "",
          "file": "",
          "beforeHooks": [],
          "afterHooks": [],
          "tests": [
            {
              "title": "should display title on home page",
              "fullTitle": "Ponyracer should display title on home page",
              "timedOut": null,
              "duration": 1051,
              "state": "passed",
              "speed": "fast",
              "pass": true,
              "fail": false,
              "pending": false,
              "context": null,
              "code": "cy.visit('/');\ncy.contains('h1', 'Ponyracer');",
              "err": {},
              "uuid": "95c1893b-951d-474d-a205-f087a1494eab",
              "parentUUID": "14620931-4fb3-4436-825d-6c1e4b9474af",
              "isHook": false,
              "skipped": false
            },
            {
              "title": "should display a navbar",
              "fullTitle": "Ponyracer should display a navbar",
              "timedOut": null,
              "duration": 409,
              "state": "passed",
              "speed": "fast",
              "pass": true,
              "fail": false,
              "pending": false,
              "context": null,
              "code": "cy.visit('/');\ncy.contains(navbarBrand, 'PonyRacer');\ncy.contains(navbarLink, 'Races');",
              "err": {},
              "uuid": "dda42f67-7fe4-452a-aa2d-ab4b82042d6a",
              "parentUUID": "14620931-4fb3-4436-825d-6c1e4b9474af",
              "isHook": false,
              "skipped": false
            },
            {
              "title": "should display a navbar collapsed on small screen",
              "fullTitle": "Ponyracer should display a navbar collapsed on small screen",
              "timedOut": null,
              "duration": 611,
              "state": "passed",
              "speed": "fast",
              "pass": true,
              "fail": false,
              "pending": false,
              "context": null,
              "code": "cy.viewport('iphone-6+');\ncy.visit('/');\ncy.contains(navbarBrand, 'PonyRacer');\ncy.get(navbarLink).should('not.be.visible');\n// toggle the navbar\ncy.get('.navbar-toggler').click();\ncy.get(navbarLink).should('be.visible');",
              "err": {},
              "uuid": "f670a963-1668-49fd-a39e-25ada75d1117",
              "parentUUID": "14620931-4fb3-4436-825d-6c1e4b9474af",
              "isHook": false,
              "skipped": false
            },
            {
              "title": "should display a race list",
              "fullTitle": "Ponyracer should display a race list",
              "timedOut": null,
              "duration": 366,
              "state": "passed",
              "speed": "fast",
              "pass": true,
              "fail": false,
              "pending": false,
              "context": null,
              "code": "cy.visit('/');\ncy.get('h2').should('have.length', 2);\ncy.get('p').should('have.length', 2).and('contain', 'ago');",
              "err": {},
              "uuid": "32597ace-d972-41b6-937b-44f113087cfa",
              "parentUUID": "14620931-4fb3-4436-825d-6c1e4b9474af",
              "isHook": false,
              "skipped": false
            },
            {
              "title": "should display ponies",
              "fullTitle": "Ponyracer should display ponies",
              "timedOut": null,
              "duration": 393,
              "state": "passed",
              "speed": "fast",
              "pass": true,
              "fail": false,
              "pending": false,
              "context": null,
              "code": "cy.visit('/');\ncy.get('figure').should('have.length', 10);\ncy.get('img').should('have.length', 10);\ncy.get('figcaption').should('have.length', 10);",
              "err": {},
              "uuid": "dc92d761-b0c0-4a2e-93f2-ccffa2e4cc37",
              "parentUUID": "14620931-4fb3-4436-825d-6c1e4b9474af",
              "isHook": false,
              "skipped": false
            }
          ],
          "suites": [],
          "passes": [
            "95c1893b-951d-474d-a205-f087a1494eab",
            "dda42f67-7fe4-452a-aa2d-ab4b82042d6a",
            "f670a963-1668-49fd-a39e-25ada75d1117",
            "32597ace-d972-41b6-937b-44f113087cfa",
            "dc92d761-b0c0-4a2e-93f2-ccffa2e4cc37"
          ],
          "failures": [],
          "pending": [],
          "skipped": [],
          "duration": 2830,
          "root": false,
          "rootEmpty": false,
          "_timeout": 2000
        }
      ],
      "passes": [],
      "failures": [],
      "pending": [],
      "skipped": [],
      "duration": 0,
      "root": true,
      "rootEmpty": true,
      "_timeout": 2000
    }
  ],
  "meta": {
    "mocha": {
      "version": "7.0.1"
    },
    "mochawesome": {
      "options": {
        "quiet": false,
        "reportFilename": "mochawesome",
        "saveHtml": false,
        "saveJson": true,
        "consoleReporter": "spec",
        "useInlineDiffs": false,
        "code": true
      },
      "version": "7.1.3"
    },
    "marge": {
      "options": {
        "reportDir": "results/mochawesome",
        "overwrite": false,
        "html": false,
        "json": true
      },
      "version": "6.2.0"
    }
  }
}